{"expireTime":9007200937156543000,"key":"create-remote-file-node-headers-https://strapiuploaddemo996.s3.eu-central-1.amazonaws.com/hero_02554df8a4.svg","val":{"x-amz-id-2":"+MB0KBRDBdQZzcQ/URJa6PlofnBYy5SXdyZp1Dp0619VlzWbHgTQIpj8y0TZM5kasofaX9MZfsmOL1wfh1zMXQ==","x-amz-request-id":"A5P3GNBRGYPECJ1F","date":"Tue, 25 Apr 2023 09:39:13 GMT","last-modified":"Sun, 09 Apr 2023 04:39:05 GMT","etag":"\"7f6c6bd3fbb2b7fb0973fdf4a19cb784\"","x-amz-server-side-encryption":"AES256","accept-ranges":"bytes","content-type":"image/svg+xml","server":"AmazonS3","content-length":"25451","connection":"close"}}